LICENCE
MANIFEST.in
README.rst
setup.cfg
setup.py
bin/rt
redtape/__init__.py
redtape/gfm.py
redtape/script.py
redtape.egg-info/PKG-INFO
redtape.egg-info/SOURCES.txt
redtape.egg-info/dependency_links.txt
redtape.egg-info/entry_points.txt
redtape.egg-info/not-zip-safe
redtape.egg-info/requires.txt
redtape.egg-info/top_level.txt
redtape/assets/basic.jinja
redtape/assets/css/bootstrap-responsive.min.css
redtape/assets/css/bootstrap.min.css
redtape/assets/css/prettify.css
redtape/assets/css/pygments.css
redtape/assets/img/glyphicons-halflings-white.png
redtape/assets/img/glyphicons-halflings.png
redtape/assets/js/bootstrap.min.js
redtape/assets/js/jquery.min.js
redtape/assets/js/lang-apollo.js
redtape/assets/js/lang-clj.js
redtape/assets/js/lang-css.js
redtape/assets/js/lang-go.js
redtape/assets/js/lang-hs.js
redtape/assets/js/lang-lisp.js
redtape/assets/js/lang-lua.js
redtape/assets/js/lang-ml.js
redtape/assets/js/lang-n.js
redtape/assets/js/lang-proto.js
redtape/assets/js/lang-scala.js
redtape/assets/js/lang-sql.js
redtape/assets/js/lang-tex.js
redtape/assets/js/lang-vb.js
redtape/assets/js/lang-vhdl.js
redtape/assets/js/lang-wiki.js
redtape/assets/js/lang-xq.js
redtape/assets/js/lang-yaml.js
redtape/assets/js/prettify.js