Metadata-Version: 1.0
Name: redtape
Version: 1.0
Summary: simple tiny document generator
Home-page: http://github.com/jmoiron/redtape
Author: Jason Moiron
Author-email: jmoiron@jmoiron.net
License: MIT
Keywords: github markdown documentation quick small simple
Platform: UNKNOWN
Classifier: Development Status :: 1 - Planning
Classifier: Operating System :: POSIX
Classifier: Environment :: Console
Classifier: License :: OSI Approved :: MIT License
